kakao/__init__.py
kakao/booking.py
kakao/channel.py
kakao/chat.py
kakao/checkIn.py
kakao/checkreg.py
kakao/config.py
kakao/cryptoManager.py
kakao/helper.py
kakao/httpApi.py
kakao/kakao.py
kakao/packet.py
kakao/writer.py
kakao/ext/commands/__init__.py
kakao/ext/commands/bot.py
kakao/ext/commands/core.py
kakao.py-0.3.0.dist-info/LICENSE
kakao.py-0.3.0.dist-info/METADATA
kakao.py-0.3.0.dist-info/WHEEL
kakao.py-0.3.0.dist-info/top_level.txt
kakao.py-0.3.0.dist-info/RECORD
