Metadata-Version: 2.1
Name: kakao.py
Version: 0.3.0
Summary: Very simple kakaotalk LOCO/HTTP API protocol wrapper for python.
Home-page: https://github.com/jhleekr/kakao.py
Author: jhleekr
Author-email: jhlee@bfy.kr
Classifier: License :: OSI Approved :: MIT License
License-File: LICENSE
Requires-Dist: pymongo
Requires-Dist: requests
Requires-Dist: pycryptodomex
